Metadata-Version: 2.1
Name: hello-world-lincs
Version: 0.1.0
Summary: Add your description here
Requires-Python: >=3.12
Requires-Dist: numpy >=2.1.3
